secml_malware/__init__.py
secml_malware/attack/__init__.py
secml_malware/attack/blackbox/__init__.py
secml_malware/attack/blackbox/c_black_box_format_exploit_evasion.py
secml_malware/attack/blackbox/c_black_box_padding_evasion.py
secml_malware/attack/blackbox/c_blackbox_header_problem.py
secml_malware/attack/blackbox/c_blackbox_headerfields_problem.py
secml_malware/attack/blackbox/c_blackbox_problem.py
secml_malware/attack/blackbox/c_gamma_evasion.py
secml_malware/attack/blackbox/c_gamma_sections_evasion.py
secml_malware/attack/blackbox/c_gamma_shift_problem.py
secml_malware/attack/blackbox/c_gammapi_evasion.py
secml_malware/attack/blackbox/c_wrapper_phi.py
secml_malware/attack/blackbox/ga/__init__.py
secml_malware/attack/blackbox/ga/c_base_genetic_engine.py
secml_malware/attack/blackbox/ga/c_nevergrad_ga.py
secml_malware/attack/blackbox/tests/__init__.py
secml_malware/attack/blackbox/tests/black_box_base_test.py
secml_malware/attack/blackbox/tests/test_black_box_attack.py
secml_malware/attack/blackbox/tests/test_nevergrad_attacks.py
secml_malware/attack/whitebox/__init__.py
secml_malware/attack/whitebox/c_discretized_bytes_evasion.py
secml_malware/attack/whitebox/c_end2end_evasion.py
secml_malware/attack/whitebox/c_extend_dos_evasion.py
secml_malware/attack/whitebox/c_fast_gradient_sign_evasion.py
secml_malware/attack/whitebox/c_format_exploit_evasion.py
secml_malware/attack/whitebox/c_header_evasion.py
secml_malware/attack/whitebox/c_headerfields_evasion.py
secml_malware/attack/whitebox/c_kreuk_evasion.py
secml_malware/attack/whitebox/c_padding_evasion.py
secml_malware/attack/whitebox/c_shift_evasion.py
secml_malware/attack/whitebox/c_slack_evasion.py
secml_malware/attack/whitebox/c_suciu_evasion.py
secml_malware/attack/whitebox/tests/__init__.py
secml_malware/attack/whitebox/tests/malware_test_base.py
secml_malware/attack/whitebox/tests/test_evasion_attack.py
secml_malware/data/goodware_samples/file1
secml_malware/data/goodware_samples/file2
secml_malware-0.4.2.dist-info/licenses/LICENSE
secml_malware-0.4.2.dist-info/METADATA
secml_malware-0.4.2.dist-info/WHEEL
secml_malware-0.4.2.dist-info/top_level.txt
secml_malware-0.4.2.dist-info/RECORD
