Metadata-Version: 2.4
Name: secml_malware
Version: 0.4.2
Home-page: https://github.com/pralab/secml_malware
Author: zangobot
Author-email: luca.demetrio@unige.it
License: GPL 3.0
Classifier: Programming Language :: Python :: 3
Classifier: License :: OSI Approved :: GNU General Public License v3 (GPLv3)
Classifier: Operating System :: OS Independent
Requires-Python: >=3.6, <3.11
License-File: LICENSE
Requires-Dist: lief
Requires-Dist: python-magic
Requires-Dist: matplotlib
Requires-Dist: numpy
Requires-Dist: seaborn
Requires-Dist: secml
Requires-Dist: lightgbm
Requires-Dist: deap
Requires-Dist: torch
Requires-Dist: torchvision
Dynamic: author
Dynamic: author-email
Dynamic: classifier
Dynamic: description
Dynamic: description-content-type
Dynamic: home-page
Dynamic: license
Dynamic: license-file
Dynamic: requires-dist
Dynamic: requires-python
